[
  {
    "id": "lal",
    "title": "Lallaba Gaara Eebbaa Irraa",
    "dataUrl": "https://raw.githubusercontent.com/PaulosDave/maaddiiH/main/books/lal_data.json",
    "templateType": "nested",
    "version": 1,
    "whatsNew": "Initial release"
  },
  {
    "id": "waadaa",
    "title": "Waaqayyo Waadaa Seeneera",
    "dataUrl": "https://raw.githubusercontent.com/PaulosDave/maaddiiH/main/books/waadaa_data.json",
    "templateType": "quotes",
    "version": 1,
    "whatsNew": "Initial yaalii fii faaava aeea release"
  },
  
  {
    "id": "wnew",
    "title": "Yaalii Fagoo",
    "coverUrl": "https://res.cloudinary.com/dnzscrtjc/image/upload/v1774503968/Picsart_26-03-25_19-33-43-717_knpc49.png",
    "dataUrl": "https://raw.githubusercontent.com/PaulosDave/maaddiiH/main/books/waadaauu_data.json",
    "templateType": "standard",
    "version": 4,
    "whatsNew": "Boqqonnaawwan kana dura keessaa afan 4 itti dabalameera",
    "description": "Qajeelfama fi gorsa hafuuraa jireenya guyyaa guyyaaf."
  }
]
